dask_ee/__init__.py
dask_ee/read.py
dask_ee/read_integrationtest.py
dask_ee/read_test.py
dask_ee/write.py
dask_ee-0.0.4.dist-info/LICENSE
dask_ee-0.0.4.dist-info/METADATA
dask_ee-0.0.4.dist-info/WHEEL
dask_ee-0.0.4.dist-info/top_level.txt
dask_ee-0.0.4.dist-info/RECORD
