Metadata-Version: 2.2
Name: dask-ee
Version: 0.0.4
Summary: Google Earth Engine FeatureCollections via Dask DataFrames.
Author: Aaron Zuspan
Author-email: Alexander Merose <al@merose.com>
License: Apache-2.0
Project-URL: Homepage, https://github.com/alxmrs/dask-ee
Project-URL: Issues, https://github.com/alxmrs/dask-ee/issues
Classifier: Development Status :: 4 - Beta
Classifier: Intended Audience :: Science/Research
Classifier: Intended Audience :: Developers
Classifier: Intended Audience :: Information Technology
Classifier: License :: OSI Approved :: Apache Software License
Classifier: Operating System :: MacOS :: MacOS X
Classifier: Operating System :: Microsoft :: Windows
Classifier: Operating System :: POSIX
Classifier: Programming Language :: Python :: 3.9
Classifier: Programming Language :: Python :: 3.10
Classifier: Programming Language :: Python :: 3.11
Classifier: Programming Language :: Python :: 3.12
Classifier: Topic :: Scientific/Engineering :: Atmospheric Science
Classifier: Topic :: Scientific/Engineering :: GIS
Classifier: Topic :: Scientific/Engineering :: Hydrology
Classifier: Topic :: Scientific/Engineering :: Oceanography
Requires-Python: >=3.8
License-File: LICENSE
Requires-Dist: earthengine-api>=0.1.374
Requires-Dist: dask[dataframe]
Requires-Dist: pandas
Provides-Extra: tests
Requires-Dist: absl-py; extra == "tests"
Requires-Dist: pytest; extra == "tests"
Requires-Dist: pyink; extra == "tests"
Provides-Extra: dev
Requires-Dist: dask-ee[tests]; extra == "dev"
Requires-Dist: build; extra == "dev"
